applicability_domain/__init__.py
applicability_domain/applicability_domain.py
applicability_domain/test.py
applicability_domain-0.1.0.dist-info/METADATA
applicability_domain-0.1.0.dist-info/WHEEL
applicability_domain-0.1.0.dist-info/top_level.txt
applicability_domain-0.1.0.dist-info/RECORD
